polyframe/__init__.py
polyframe/direction.py
polyframe/frame_registry.py
polyframe/transform.py
polyframe/utils.py
polyframe-0.1.5.dist-info/licenses/LICENSE
polyframe-0.1.5.dist-info/METADATA
polyframe-0.1.5.dist-info/WHEEL
polyframe-0.1.5.dist-info/top_level.txt
polyframe-0.1.5.dist-info/RECORD
