Metadata-Version: 2.4
Name: polyframe
Version: 0.1.5
Summary: A modern python library for 3D homogenous transforms and coordinate system utilities.
Author-email: Nathan Spencer <nathanss1997@gmail.com>
License:                                  Apache License
Keywords: geometry,transforms,3d,coordinate systems,homogeneous,pose,robotics
Classifier: Development Status :: 4 - Beta
Classifier: Intended Audience :: Developers
Classifier: License :: OSI Approved :: Apache Software License
Classifier: Programming Language :: Python :: 3
Classifier: Programming Language :: Python :: 3.8
Classifier: Programming Language :: Python :: 3.9
Classifier: Programming Language :: Python :: 3.10
Classifier: Programming Language :: Python :: 3.11
Classifier: Programming Language :: Python :: 3.12
License-File: LICENSE
Requires-Dist: numpy
Requires-Dist: numba
Dynamic: license-file
